{ "name": "includes/party.proto", "package": "com.ankama.dofus.server.game.protocol.party", "dependency": [ "includes/common.proto" ], "messageType": [ { "name": "PartyInvitationRequest", "field": [ { "name": "target", "number": 1, "label": "LABEL_OPTIONAL", "type": "TYPE_MESSAGE", "typeName": ".com.ankama.dofus.server.game.protocol.common.PlayerSearch" }, { "name": "party_type", "number": 2, "label": "LABEL_OPTIONAL", "type": "TYPE_ENUM", "typeName": ".com.ankama.dofus.server.game.protocol.party.PartyType" } ] }, { "name": "PartyInvitationDetailsRequest", "field": [ { "name": "party_id", "number": 1, "label": "LABEL_OPTIONAL", "type": "TYPE_INT32" } ] }, { "name": "PartyInvitationAcceptRequest", "field": [ { "name": "party_id", "number": 1, "label": "LABEL_OPTIONAL", "type": "TYPE_INT32" } ] }, { "name": "PartyInvitationRefuseRequest", "field": [ { "name": "party_id", "number": 1, "label": "LABEL_OPTIONAL", "type": "TYPE_INT32" } ] }, { "name": "PartyInvitationCancelRequest", "field": [ { "name": "party_id", "number": 1, "label": "LABEL_OPTIONAL", "type": "TYPE_INT32" }, { "name": "guest_id", "number": 2, "label": "LABEL_OPTIONAL", "type": "TYPE_INT64" } ] }, { "name": "PartyAbdicateThroneRequest", "field": [ { "name": "party_id", "number": 1, "label": "LABEL_OPTIONAL", "type": "TYPE_INT32" }, { "name": "player_id", "number": 2, "label": "LABEL_OPTIONAL", "type": "TYPE_INT64" } ] }, { "name": "PartyFollowMemberRequest", "field": [ { "name": "party_id", "number": 1, "label": "LABEL_OPTIONAL", "type": "TYPE_INT32" }, { "name": "player_id", "number": 2, "label": "LABEL_OPTIONAL", "type": "TYPE_INT64" }, { "name": "enabled", "number": 3, "label": "LABEL_OPTIONAL", "type": "TYPE_BOOL", "oneofIndex": 0, "proto3Optional": true } ], "oneofDecl": [ { "name": "_enabled" } ] }, { "name": "PartyStopFollowMemberRequest", "field": [ { "name": "party_id", "number": 1, "label": "LABEL_OPTIONAL", "type": "TYPE_INT32" }, { "name": "player_id", "number": 2, "label": "LABEL_OPTIONAL", "type": "TYPE_INT64" } ] }, { "name": "PartyLocateMembersRequest", "field": [ { "name": "party_id", "number": 1, "label": "LABEL_OPTIONAL", "type": "TYPE_INT32" } ] }, { "name": "PartyLeaveRequest", "field": [ { "name": "party_id", "number": 1, "label": "LABEL_OPTIONAL", "type": "TYPE_INT32" } ] }, { "name": "PartyKickRequest", "field": [ { "name": "party_id", "number": 1, "label": "LABEL_OPTIONAL", "type": "TYPE_INT32" }, { "name": "player_id", "number": 2, "label": "LABEL_OPTIONAL", "type": "TYPE_INT64" } ] }, { "name": "PartyPledgeLoyaltyRequest", "field": [ { "name": "party_id", "number": 1, "label": "LABEL_OPTIONAL", "type": "TYPE_INT32" }, { "name": "loyal", "number": 2, "label": "LABEL_OPTIONAL", "type": "TYPE_BOOL" } ] }, { "name": "PartyNameSetRequest", "field": [ { "name": "party_id", "number": 1, "label": "LABEL_OPTIONAL", "type": "TYPE_INT32" }, { "name": "name", "number": 2, "label": "LABEL_OPTIONAL", "type": "TYPE_STRING" } ] }, { "name": "PartyInvitationEvent", "field": [ { "name": "party_id", "number": 1, "label": "LABEL_OPTIONAL", "type": "TYPE_INT32" }, { "name": "party_type", "number": 2, "label": "LABEL_OPTIONAL", "type": "TYPE_ENUM", "typeName": ".com.ankama.dofus.server.game.protocol.party.PartyType" }, { "name": "party_name", "number": 3, "label": "LABEL_OPTIONAL", "type": "TYPE_STRING" }, { "name": "max_participants", "number": 4, "label": "LABEL_OPTIONAL", "type": "TYPE_INT32" }, { "name": "from_player_id", "number": 5, "label": "LABEL_OPTIONAL", "type": "TYPE_INT64" }, { "name": "from_player_name", "number": 6, "label": "LABEL_OPTIONAL", "type": "TYPE_STRING" }, { "name": "to_player_id", "number": 7, "label": "LABEL_OPTIONAL", "type": "TYPE_INT64" } ] }, { "name": "PartyInvitationDetailsEvent", "field": [ { "name": "party_id", "number": 1, "label": "LABEL_OPTIONAL", "type": "TYPE_INT32" }, { "name": "party_type", "number": 2, "label": "LABEL_OPTIONAL", "type": "TYPE_ENUM", "typeName": ".com.ankama.dofus.server.game.protocol.party.PartyType" }, { "name": "party_name", "number": 3, "label": "LABEL_OPTIONAL", "type": "TYPE_STRING" }, { "name": "from_player_id", "number": 4, "label": "LABEL_OPTIONAL", "type": "TYPE_INT64" }, { "name": "from_player_name", "number": 5, "label": "LABEL_OPTIONAL", "type": "TYPE_STRING" }, { "name": "leader_id", "number": 6, "label": "LABEL_OPTIONAL", "type": "TYPE_INT64" }, { "name": "members", "number": 7, "label": "LABEL_REPEATED", "type": "TYPE_MESSAGE", "typeName": ".com.ankama.dofus.server.game.protocol.common.Character" }, { "name": "guests", "number": 8, "label": "LABEL_REPEATED", "type": "TYPE_MESSAGE", "typeName": ".com.ankama.dofus.server.game.protocol.party.PartyGuest" } ] }, { "name": "PartyInvitationCancelledForGuestEvent", "field": [ { "name": "party_id", "number": 1, "label": "LABEL_OPTIONAL", "type": "TYPE_INT32" }, { "name": "canceller_id", "number": 2, "label": "LABEL_OPTIONAL", "type": "TYPE_INT64" } ] }, { "name": "PartyInvitationCancelledEvent", "field": [ { "name": "party_id", "number": 1, "label": "LABEL_OPTIONAL", "type": "TYPE_INT32" }, { "name": "canceller_id", "number": 2, "label": "LABEL_OPTIONAL", "type": "TYPE_INT64" }, { "name": "guest_id", "number": 3, "label": "LABEL_OPTIONAL", "type": "TYPE_INT64" } ] }, { "name": "PartyInvitationRefusedEvent", "field": [ { "name": "party_id", "number": 1, "label": "LABEL_OPTIONAL", "type": "TYPE_INT32" }, { "name": "guest_id", "number": 2, "label": "LABEL_OPTIONAL", "type": "TYPE_INT64" } ] }, { "name": "PartyJoinErrorEvent", "field": [ { "name": "party_id", "number": 1, "label": "LABEL_OPTIONAL", "type": "TYPE_INT32" }, { "name": "reason", "number": 2, "label": "LABEL_OPTIONAL", "type": "TYPE_ENUM", "typeName": ".com.ankama.dofus.server.game.protocol.party.PartyJoinErrorEvent.PartyJoinError" } ], "enumType": [ { "name": "PartyJoinError", "value": [ { "name": "UNKNOWN", "number": 0 }, { "name": "PLAYER_NOT_FOUND", "number": 1 }, { "name": "PARTY_NOT_FOUND", "number": 2 }, { "name": "PARTY_FULL", "number": 3 }, { "name": "PLAYER_BUSY", "number": 4 }, { "name": "PLAYER_ALREADY_INVITED", "number": 5 }, { "name": "PLAYER_TOO_SOLICITED", "number": 6 }, { "name": "PLAYER_LOYAL", "number": 7 }, { "name": "UNMODIFIABLE", "number": 8 }, { "name": "UNMET_CRITERION", "number": 9 }, { "name": "NOT_ENOUGH_ROOM", "number": 10 }, { "name": "COMPOSITION_CHANGED", "number": 11 }, { "name": "PLAYER_IN_TUTORIAL", "number": 12 } ] } ] }, { "name": "PartyJoinEvent", "field": [ { "name": "party_id", "number": 1, "label": "LABEL_OPTIONAL", "type": "TYPE_INT32" }, { "name": "party_type", "number": 2, "label": "LABEL_OPTIONAL", "type": "TYPE_ENUM", "typeName": ".com.ankama.dofus.server.game.protocol.party.PartyType" }, { "name": "leader_id", "number": 3, "label": "LABEL_OPTIONAL", "type": "TYPE_INT64" }, { "name": "max_participants", "number": 4, "label": "LABEL_OPTIONAL", "type": "TYPE_INT32" }, { "name": "members", "number": 5, "label": "LABEL_REPEATED", "type": "TYPE_MESSAGE", "typeName": ".com.ankama.dofus.server.game.protocol.common.Character" }, { "name": "guests", "number": 6, "label": "LABEL_REPEATED", "type": "TYPE_MESSAGE", "typeName": ".com.ankama.dofus.server.game.protocol.party.PartyGuest" }, { "name": "restricted", "number": 7, "label": "LABEL_OPTIONAL", "type": "TYPE_BOOL" }, { "name": "party_name", "number": 8, "label": "LABEL_OPTIONAL", "type": "TYPE_STRING" } ] }, { "name": "PartyNewGuestEvent", "field": [ { "name": "party_id", "number": 1, "label": "LABEL_OPTIONAL", "type": "TYPE_INT32" }, { "name": "guest", "number": 2, "label": "LABEL_OPTIONAL", "type": "TYPE_MESSAGE", "typeName": ".com.ankama.dofus.server.game.protocol.party.PartyGuest" } ] }, { "name": "PartyMemberUpdateEvent", "field": [ { "name": "party_id", "number": 1, "label": "LABEL_OPTIONAL", "type": "TYPE_INT32" }, { "name": "member", "number": 2, "label": "LABEL_OPTIONAL", "type": "TYPE_MESSAGE", "typeName": ".com.ankama.dofus.server.game.protocol.common.Character" } ] }, { "name": "PartyNewMemberEvent", "field": [ { "name": "party_id", "number": 1, "label": "LABEL_OPTIONAL", "type": "TYPE_INT32" }, { "name": "member", "number": 2, "label": "LABEL_OPTIONAL", "type": "TYPE_MESSAGE", "typeName": ".com.ankama.dofus.server.game.protocol.common.Character" } ] }, { "name": "PartyMemberUpdateLightEvent", "field": [ { "name": "party_id", "number": 1, "label": "LABEL_OPTIONAL", "type": "TYPE_INT32" }, { "name": "player_id", "number": 2, "label": "LABEL_OPTIONAL", "type": "TYPE_INT64" }, { "name": "commons_information", "number": 3, "label": "LABEL_OPTIONAL", "type": "TYPE_MESSAGE", "typeName": ".com.ankama.dofus.server.game.protocol.common.PartyUpdateCommonsInformation" }, { "name": "index", "number": 4, "label": "LABEL_OPTIONAL", "type": "TYPE_INT32", "oneofIndex": 0, "proto3Optional": true } ], "oneofDecl": [ { "name": "_index" } ] }, { "name": "PartyMemberRemoveEvent", "field": [ { "name": "party_id", "number": 1, "label": "LABEL_OPTIONAL", "type": "TYPE_INT32" }, { "name": "leaving_player_id", "number": 2, "label": "LABEL_OPTIONAL", "type": "TYPE_INT64" }, { "name": "kicker_id", "number": 3, "label": "LABEL_OPTIONAL", "type": "TYPE_INT64", "oneofIndex": 0, "proto3Optional": true } ], "oneofDecl": [ { "name": "_kicker_id" } ] }, { "name": "PartyLeaderUpdateEvent", "field": [ { "name": "party_id", "number": 1, "label": "LABEL_OPTIONAL", "type": "TYPE_INT32" }, { "name": "party_leader_id", "number": 2, "label": "LABEL_OPTIONAL", "type": "TYPE_INT64" } ] }, { "name": "PartyFollowStatusUpdateEvent", "field": [ { "name": "party_id", "number": 1, "label": "LABEL_OPTIONAL", "type": "TYPE_INT32" }, { "name": "success", "number": 2, "label": "LABEL_OPTIONAL", "type": "TYPE_BOOL" }, { "name": "is_followed", "number": 3, "label": "LABEL_OPTIONAL", "type": "TYPE_BOOL" }, { "name": "followed_id", "number": 4, "label": "LABEL_OPTIONAL", "type": "TYPE_INT64" } ] }, { "name": "PartyLeaveEvent", "field": [ { "name": "party_id", "number": 1, "label": "LABEL_OPTIONAL", "type": "TYPE_INT32" } ] }, { "name": "PartyKickedByEvent", "field": [ { "name": "party_id", "number": 1, "label": "LABEL_OPTIONAL", "type": "TYPE_INT32" }, { "name": "kicker_id", "number": 2, "label": "LABEL_OPTIONAL", "type": "TYPE_INT64" } ] }, { "name": "PartyRestrictedEvent", "field": [ { "name": "party_id", "number": 1, "label": "LABEL_OPTIONAL", "type": "TYPE_INT32" }, { "name": "restricted", "number": 2, "label": "LABEL_OPTIONAL", "type": "TYPE_BOOL" } ] }, { "name": "PartyDeletedEvent", "field": [ { "name": "party_id", "number": 1, "label": "LABEL_OPTIONAL", "type": "TYPE_INT32" } ] }, { "name": "PartyLoyaltyStatusEvent", "field": [ { "name": "party_id", "number": 1, "label": "LABEL_OPTIONAL", "type": "TYPE_INT32" }, { "name": "loyal", "number": 2, "label": "LABEL_OPTIONAL", "type": "TYPE_BOOL" } ] }, { "name": "PartyMemberInFightEvent", "field": [ { "name": "party_id", "number": 1, "label": "LABEL_OPTIONAL", "type": "TYPE_INT32" }, { "name": "reason", "number": 2, "label": "LABEL_OPTIONAL", "type": "TYPE_ENUM", "typeName": ".com.ankama.dofus.server.game.protocol.party.PartyMemberInFightCause" }, { "name": "member_id", "number": 3, "label": "LABEL_OPTIONAL", "type": "TYPE_INT64" }, { "name": "member_account_id", "number": 4, "label": "LABEL_OPTIONAL", "type": "TYPE_INT64" }, { "name": "member_name", "number": 5, "label": "LABEL_OPTIONAL", "type": "TYPE_STRING" }, { "name": "fight_id", "number": 6, "label": "LABEL_OPTIONAL", "type": "TYPE_INT32" }, { "name": "time_before_fight_start", "number": 7, "label": "LABEL_OPTIONAL", "type": "TYPE_INT32" }, { "name": "standard_fight_map", "number": 8, "label": "LABEL_OPTIONAL", "type": "TYPE_MESSAGE", "typeName": ".com.ankama.dofus.server.game.protocol.common.MapExtendedCoordinates" } ] }, { "name": "PartyMemberInBreachFightEvent", "field": [ { "name": "party_id", "number": 1, "label": "LABEL_OPTIONAL", "type": "TYPE_INT32" }, { "name": "reason", "number": 2, "label": "LABEL_OPTIONAL", "type": "TYPE_ENUM", "typeName": ".com.ankama.dofus.server.game.protocol.party.PartyMemberInFightCause" }, { "name": "member_id", "number": 3, "label": "LABEL_OPTIONAL", "type": "TYPE_INT64" }, { "name": "member_account_id", "number": 4, "label": "LABEL_OPTIONAL", "type": "TYPE_INT64" }, { "name": "member_name", "number": 5, "label": "LABEL_OPTIONAL", "type": "TYPE_STRING" }, { "name": "fight_id", "number": 6, "label": "LABEL_OPTIONAL", "type": "TYPE_INT32" }, { "name": "time_before_fight_start", "number": 7, "label": "LABEL_OPTIONAL", "type": "TYPE_INT32" }, { "name": "floor", "number": 8, "label": "LABEL_OPTIONAL", "type": "TYPE_INT32" }, { "name": "room", "number": 9, "label": "LABEL_OPTIONAL", "type": "TYPE_INT32" } ] }, { "name": "PartyNameUpdateEvent", "field": [ { "name": "party_id", "number": 1, "label": "LABEL_OPTIONAL", "type": "TYPE_INT32" }, { "name": "name", "number": 2, "label": "LABEL_OPTIONAL", "type": "TYPE_STRING" } ] }, { "name": "PartyNameSetErrorEvent", "field": [ { "name": "party_id", "number": 1, "label": "LABEL_OPTIONAL", "type": "TYPE_INT32" }, { "name": "result", "number": 2, "label": "LABEL_OPTIONAL", "type": "TYPE_ENUM", "typeName": ".com.ankama.dofus.server.game.protocol.party.PartyNameSetErrorEvent.PartyNameError" } ], "enumType": [ { "name": "PartyNameError", "value": [ { "name": "UNDEFINED_ERROR", "number": 0 }, { "name": "INVALID", "number": 1 }, { "name": "ALREADY_USED", "number": 2 }, { "name": "UNALLOWED_RIGHTS", "number": 3 }, { "name": "UNALLOWED_NOW", "number": 4 } ] } ] }, { "name": "PartyGuest", "field": [ { "name": "player_id", "number": 1, "label": "LABEL_OPTIONAL", "type": "TYPE_INT64" }, { "name": "host_id", "number": 2, "label": "LABEL_OPTIONAL", "type": "TYPE_INT64" }, { "name": "name", "number": 3, "label": "LABEL_OPTIONAL", "type": "TYPE_STRING" }, { "name": "look", "number": 4, "label": "LABEL_OPTIONAL", "type": "TYPE_MESSAGE", "typeName": ".com.ankama.dofus.server.game.protocol.common.EntityLook" }, { "name": "breed", "number": 5, "label": "LABEL_OPTIONAL", "type": "TYPE_INT32" }, { "name": "gender", "number": 6, "label": "LABEL_OPTIONAL", "type": "TYPE_ENUM", "typeName": ".com.ankama.dofus.server.game.protocol.common.Gender" }, { "name": "status", "number": 7, "label": "LABEL_OPTIONAL", "type": "TYPE_MESSAGE", "typeName": ".com.ankama.dofus.server.game.protocol.common.CharacterStatus" }, { "name": "entities", "number": 8, "label": "LABEL_REPEATED", "type": "TYPE_MESSAGE", "typeName": ".com.ankama.dofus.server.game.protocol.common.PartyEntity" } ] } ], "enumType": [ { "name": "PartyMemberInFightCause", "value": [ { "name": "UNKNOWN", "number": 0 }, { "name": "MONSTER_ATTACK", "number": 1 }, { "name": "PLAYER_ATTACK", "number": 2 }, { "name": "MEMBER_ATTACKED_PLAYERS", "number": 3 }, { "name": "MEMBER_CHALLENGE", "number": 4 } ] }, { "name": "PartyType", "value": [ { "name": "UNDEFINED", "number": 0 }, { "name": "CLASSICAL", "number": 1 }, { "name": "ARENA", "number": 2 } ] } ], "options": { "javaMultipleFiles": true }, "syntax": "proto3" }